django_windowsauthtoken/__init__.py
django_windowsauthtoken/formatters.py
django_windowsauthtoken/middleware.py
django_windowsauthtoken/views.py
django_windowsauthtoken-0.1.2.dist-info/licenses/LICENSE
django_windowsauthtoken-0.1.2.dist-info/METADATA
django_windowsauthtoken-0.1.2.dist-info/WHEEL
django_windowsauthtoken-0.1.2.dist-info/top_level.txt
django_windowsauthtoken-0.1.2.dist-info/RECORD
