Metadata-Version: 2.4
Name: django-windowsauthtoken
Version: 0.1.2
Summary: IIS Windows Authentication Token handling for Django
Author-email: Tom Hendrikx <tom@whyscream.net>
License-Expression: BSD-3-Clause
Project-URL: Homepage, https://github.com/whyscream/django-windowsauthtoken
Project-URL: Issues, https://github.com/whyscream/django-windowsauthtoken/issues
Classifier: Development Status :: 4 - Beta
Classifier: Programming Language :: Python :: 3.9
Classifier: Programming Language :: Python :: 3.10
Classifier: Programming Language :: Python :: 3.11
Classifier: Programming Language :: Python :: 3.12
Classifier: Programming Language :: Python :: 3.13
Classifier: Programming Language :: Python :: 3.14
Classifier: Framework :: Django
Classifier: Intended Audience :: Developers
Classifier: Operating System :: Microsoft :: Windows
Requires-Python: >=3.9
License-File: LICENSE
Requires-Dist: django>=4.2
Requires-Dist: pywin32>=311; sys_platform == "win32"
Dynamic: license-file
